olink/__init__.py
olink/clientnode.py
olink/remotenode.py
olink/core/__init__.py
olink/core/node.py
olink/core/protocol.py
olink/core/types.py
olink/mocks/__init__.py
olink/mocks/mocksink.py
olink/mocks/mocksource.py
objectlink_core-0.2.dist-info/LICENSE
objectlink_core-0.2.dist-info/METADATA
objectlink_core-0.2.dist-info/WHEEL
objectlink_core-0.2.dist-info/top_level.txt
objectlink_core-0.2.dist-info/RECORD
